cow_api/__init__.py
cow_api/main.py
cow_api/models.py
tests/__init__.py
tests/test_main.py
cow_api-0.1.1.dist-info/METADATA
cow_api-0.1.1.dist-info/WHEEL
cow_api-0.1.1.dist-info/top_level.txt
cow_api-0.1.1.dist-info/RECORD
